{
    "enwiki": {
        "models": {
            "articlequality": {
                "version": "0.8.2"
            }
        },
        "scores": {
            "705322126": {
                "articlequality": {
                    "score": {
                        "prediction": "Stub",
                        "probability": {
                            "B": 0.0060267098300485905,
                            "C": 0.008818081535568904,
                            "FA": 0.001217564911597732,
                            "GA": 0.00257280944673717,
                            "Start": 0.017285391853622007,
                            "Stub": 0.9640794424224256
                        }
                    }
                }
            },
            "710615823": {
                "articlequality": {
                    "score": {
                        "prediction": "Stub",
                        "probability": {
                            "B": 0.007082037380267073,
                            "C": 0.0075457237569028805,
                            "FA": 0.0012040116184036285,
                            "GA": 0.001875055723277095,
                            "Start": 0.016817389311458278,
                            "Stub": 0.9654757822096911
                        }
                    }
                }
            },
            "714904933": {
                "articlequality": {
                    "score": {
                        "prediction": "Stub",
                        "probability": {
                            "B": 0.006115441674801195,
                            "C": 0.008660435169150918,
                            "FA": 0.0012191507738488264,
                            "GA": 0.0025577763287102494,
                            "Start": 0.015524275233798911,
                            "Stub": 0.96592292081969
                        }
                    }
                }
            },
            "718382045": {
                "articlequality": {
                    "score": {
                        "prediction": "Stub",
                        "probability": {
                            "B": 0.007345618624014637,
                            "C": 0.011993137459563343,
                            "FA": 0.0013693256034268402,
                            "GA": 0.0031596814985988347,
                            "Start": 0.044975745225998606,
                            "Stub": 0.9311564915883976
                        }
                    }
                }
            },
            "721725804": {
                "articlequality": {
                    "score": {
                        "prediction": "Stub",
                        "probability": {
                            "B": 0.005103136714824654,
                            "C": 0.006925878464492214,
                            "FA": 0.001028178024736665,
                            "GA": 0.0021525068511658784,
                            "Start": 0.011907726487861073,
                            "Stub": 0.9728825734569195
                        }
                    }
                }
            },
            "725174976": {
                "articlequality": {
                    "score": {
                        "prediction": "Stub",
                        "probability": {
                            "B": 0.0072987044552563505,
                            "C": 0.01014893640625411,
                            "FA": 0.0014232582332083608,
                            "GA": 0.0027200812508038027,
                            "Start": 0.0315924570064731,
                            "Stub": 0.9468165626480043
                        }
                    }
                }
            },
            "731193147": {
                "articlequality": {
                    "score": {
                        "prediction": "Start",
                        "probability": {
                            "B": 0.02604122362438219,
                            "C": 0.11874927270076274,
                            "FA": 0.004095619374647639,
                            "GA": 0.01186724862589341,
                            "Start": 0.5096615997962266,
                            "Stub": 0.32958503587808735
                        }
                    }
                }
            },
            "737795855": {
                "articlequality": {
                    "score": {
                        "prediction": "Stub",
                        "probability": {
                            "B": 0.010578715960108176,
                            "C": 0.01797117215330177,
                            "FA": 0.0018561410139028216,
                            "GA": 0.0042540643753988215,
                            "Start": 0.08790174263266357,
                            "Stub": 0.8774381638646248
                        }
                    }
                }
            },
            "743654952": {
                "articlequality": {
                    "score": {
                        "prediction": "Start",
                        "probability": {
                            "B": 0.02471878496965179,
                            "C": 0.025496659981823454,
                            "FA": 0.0037145756440655877,
                            "GA": 0.006058205330768201,
                            "Start": 0.5736084135052939,
                            "Stub": 0.366403360568397
                        }
                    }
                }
            },
            "748420498": {
                "articlequality": {
                    "score": {
                        "prediction": "Stub",
                        "probability": {
                            "B": 0.010632413209393508,
                            "C": 0.013260296640698341,
                            "FA": 0.0018769199346936303,
                            "GA": 0.0036446671189005967,
                            "Start": 0.057721850261342834,
                            "Stub": 0.9128638528349711
                        }
                    }
                }
            },
            "753140661": {
                "articlequality": {
                    "score": {
                        "prediction": "Stub",
                        "probability": {
                            "B": 0.005692240524964441,
                            "C": 0.006876420034497347,
                            "FA": 0.001041617568369127,
                            "GA": 0.0018022366264361174,
                            "Start": 0.013881314635871592,
                            "Stub": 0.9707061706098614
                        }
                    }
                }
            },
            "757008140": {
                "articlequality": {
                    "score": {
                        "prediction": "Stub",
                        "probability": {
                            "B": 0.012517548286702594,
                            "C": 0.027073801083371908,
                            "FA": 0.0024355891432516,
                            "GA": 0.006079718804285426,
                            "Start": 0.13242693911754114,
                            "Stub": 0.8194664035648472
                        }
                    }
                }
            },
            "757443215": {
                "articlequality": {
                    "score": {
                        "prediction": "Stub",
                        "probability": {
                            "B": 0.006878307420095495,
                            "C": 0.007580480343174634,
                            "FA": 0.0013895654232791285,
                            "GA": 0.0019737269952748737,
                            "Start": 0.019866574646886057,
                            "Stub": 0.9623113451712899
                        }
                    }
                }
            },
            "760031780": {
                "articlequality": {
                    "score": {
                        "prediction": "Stub",
                        "probability": {
                            "B": 0.01074439033292148,
                            "C": 0.020944897661450752,
                            "FA": 0.0017864031346549656,
                            "GA": 0.0037947174995027803,
                            "Start": 0.14140574734804748,
                            "Stub": 0.8213238440234224
                        }
                    }
                }
            },
            "764856579": {
                "articlequality": {
                    "score": {
                        "prediction": "Stub",
                        "probability": {
                            "B": 0.006049500213508594,
                            "C": 0.00672326824435212,
                            "FA": 0.0010908712667046518,
                            "GA": 0.0017150078979234656,
                            "Start": 0.014150661719154701,
                            "Stub": 0.9702706906583565
                        }
                    }
                }
            },
            "768706438": {
                "articlequality": {
                    "score": {
                        "prediction": "C",
                        "probability": {
                            "B": 0.09579636465494677,
                            "C": 0.4437117660520585,
                            "FA": 0.0037843452639892165,
                            "GA": 0.02289356380549983,
                            "Start": 0.4274732959991134,
                            "Stub": 0.006340664224392229
                        }
                    }
                }
            },
            "772092345": {
                "articlequality": {
                    "score": {
                        "prediction": "Start",
                        "probability": {
                            "B": 0.05243097723510354,
                            "C": 0.21602575852569708,
                            "FA": 0.0046384948500744795,
                            "GA": 0.010353860516673336,
                            "Start": 0.6882832009295737,
                            "Stub": 0.028267707942877852
                        }
                    }
                }
            },
            "775688533": {
                "articlequality": {
                    "score": {
                        "prediction": "Stub",
                        "probability": {
                            "B": 0.008221449816054202,
                            "C": 0.010647878533620885,
                            "FA": 0.0014702208195659728,
                            "GA": 0.002398177339581437,
                            "Start": 0.05159157198427269,
                            "Stub": 0.9256707015069049
                        }
                    }
                }
            },
            "778607327": {
                "articlequality": {
                    "score": {
                        "prediction": "Start",
                        "probability": {
                            "B": 0.1502780554153277,
                            "C": 0.2504087410613593,
                            "FA": 0.005145976204659314,
                            "GA": 0.03209206114576963,
                            "Start": 0.5379648536652769,
                            "Stub": 0.02411031250760714
                        }
                    }
                }
            },
            "780743874": {
                "articlequality": {
                    "score": {
                        "prediction": "Stub",
                        "probability": {
                            "B": 0.011664287707061497,
                            "C": 0.019048896774594214,
                            "FA": 0.00206519527650455,
                            "GA": 0.0038620842774178617,
                            "Start": 0.11278362282723861,
                            "Stub": 0.8505759131371833
                        }
                    }
                }
            },
            "783347744": {
                "articlequality": {
                    "score": {
                        "prediction": "Start",
                        "probability": {
                            "B": 0.06555939516824513,
                            "C": 0.11305298939509041,
                            "FA": 0.006332827460980586,
                            "GA": 0.013449718390564223,
                            "Start": 0.5912174006492111,
                            "Stub": 0.21038766893590863
                        }
                    }
                }
            },
            "785298835": {
                "articlequality": {
                    "score": {
                        "prediction": "Start",
                        "probability": {
                            "B": 0.09061701610509967,
                            "C": 0.29178103486034584,
                            "FA": 0.0043001899417600435,
                            "GA": 0.008795002986058176,
                            "Start": 0.5833766516514418,
                            "Stub": 0.021130104455294396
                        }
                    }
                }
            },
            "787252025": {
                "articlequality": {
                    "score": {
                        "prediction": "Stub",
                        "probability": {
                            "B": 0.09223366005175297,
                            "C": 0.1351143367241999,
                            "FA": 0.004935390115114526,
                            "GA": 0.030681576009311807,
                            "Start": 0.3119917703605776,
                            "Stub": 0.42504326673904325
                        }
                    }
                }
            },
            "788177506": {
                "articlequality": {
                    "score": {
                        "prediction": "Stub",
                        "probability": {
                            "B": 0.00613698611372457,
                            "C": 0.007402583488648941,
                            "FA": 0.0010849052087054634,
                            "GA": 0.0019365537051383667,
                            "Start": 0.015478896818061064,
                            "Stub": 0.9679600746657215
                        }
                    }
                }
            },
            "788780040": {
                "articlequality": {
                    "score": {
                        "prediction": "Stub",
                        "probability": {
                            "B": 0.0226037871963634,
                            "C": 0.023140006932627553,
                            "FA": 0.0035616757066737675,
                            "GA": 0.00532575172413113,
                            "Start": 0.43445373177619545,
                            "Stub": 0.5109150466640088
                        }
                    }
                }
            },
            "788878455": {
                "articlequality": {
                    "score": {
                        "prediction": "Stub",
                        "probability": {
                            "B": 0.012079203379379294,
                            "C": 0.019296410033627427,
                            "FA": 0.0020055621923881963,
                            "GA": 0.0031586721942653247,
                            "Start": 0.07299794784210352,
                            "Stub": 0.8904622043582363
                        }
                    }
                }
            },
            "789150016": {
                "articlequality": {
                    "score": {
                        "prediction": "Stub",
                        "probability": {
                            "B": 0.008901321895946845,
                            "C": 0.01019045644671824,
                            "FA": 0.001580134464230177,
                            "GA": 0.002454777850864298,
                            "Start": 0.04512486145895583,
                            "Stub": 0.9317484478832846
                        }
                    }
                }
            },
            "789304595": {
                "articlequality": {
                    "score": {
                        "prediction": "Stub",
                        "probability": {
                            "B": 0.008792788336442205,
                            "C": 0.011905716891253651,
                            "FA": 0.0016986480303203876,
                            "GA": 0.0026560308418043304,
                            "Start": 0.03506104456995577,
                            "Stub": 0.9398857713302237
                        }
                    }
                }
            },
            "789711985": {
                "articlequality": {
                    "score": {
                        "prediction": "C",
                        "probability": {
                            "B": 0.10731402598171252,
                            "C": 0.6821372787593025,
                            "FA": 0.005072117450908878,
                            "GA": 0.018407420115028283,
                            "Start": 0.18285282561404323,
                            "Stub": 0.0042163320790045734
                        }
                    }
                }
            },
            "790410737": {
                "articlequality": {
                    "score": {
                        "prediction": "Stub",
                        "probability": {
                            "B": 0.010416324845025129,
                            "C": 0.015035303251064587,
                            "FA": 0.002074273010058924,
                            "GA": 0.003710496270380119,
                            "Start": 0.15760798608763152,
                            "Stub": 0.8111556165358396
                        }
                    }
                }
            },
            "791692346": {
                "articlequality": {
                    "score": {
                        "prediction": "Start",
                        "probability": {
                            "B": 0.08722926764703998,
                            "C": 0.09637797221188026,
                            "FA": 0.004782602558555913,
                            "GA": 0.01408019154241751,
                            "Start": 0.6879976792643823,
                            "Stub": 0.10953228677572399
                        }
                    }
                }
            },
            "793218160": {
                "articlequality": {
                    "score": {
                        "prediction": "C",
                        "probability": {
                            "B": 0.17616411444022181,
                            "C": 0.585938263655916,
                            "FA": 0.006976334335220291,
                            "GA": 0.09758524023764809,
                            "Start": 0.12592284453809607,
                            "Stub": 0.00741320279289784
                        }
                    }
                }
            },
            "794593033": {
                "articlequality": {
                    "score": {
                        "prediction": "Stub",
                        "probability": {
                            "B": 0.017712408511813715,
                            "C": 0.02607631761858809,
                            "FA": 0.003162505930898358,
                            "GA": 0.005343973180786774,
                            "Start": 0.3240825277511653,
                            "Stub": 0.6236222670067478
                        }
                    }
                }
            },
            "795801882": {
                "articlequality": {
                    "score": {
                        "prediction": "Stub",
                        "probability": {
                            "B": 0.007011804078724227,
                            "C": 0.00961696170664404,
                            "FA": 0.0013865141428724703,
                            "GA": 0.002676057927163171,
                            "Start": 0.028670454879392324,
                            "Stub": 0.9506382072652038
                        }
                    }
                }
            },
            "796920345": {
                "articlequality": {
                    "score": {
                        "prediction": "Start",
                        "probability": {
                            "B": 0.02541317769141109,
                            "C": 0.04227517577830436,
                            "FA": 0.004748390613204633,
                            "GA": 0.007610248422386537,
                            "Start": 0.5246864170415986,
                            "Stub": 0.39526659045309476
                        }
                    }
                }
            },
            "797911629": {
                "articlequality": {
                    "score": {
                        "prediction": "C",
                        "probability": {
                            "B": 0.2986670465981408,
                            "C": 0.5556359290643829,
                            "FA": 0.008770634889435122,
                            "GA": 0.06230893090366996,
                            "Start": 0.06846940811830084,
                            "Stub": 0.006148050426070476
                        }
                    }
                }
            },
            "798876269": {
                "articlequality": {
                    "score": {
                        "prediction": "Stub",
                        "probability": {
                            "B": 0.010020086918626393,
                            "C": 0.01911284740519861,
                            "FA": 0.0018747519932306195,
                            "GA": 0.004118614510214054,
                            "Start": 0.09419640484252029,
                            "Stub": 0.87067729433021
                        }
                    }
                }
            },
            "799714270": {
                "articlequality": {
                    "score": {
                        "prediction": "C",
                        "probability": {
                            "B": 0.2012985319637018,
                            "C": 0.5015772204883115,
                            "FA": 0.014117677219077675,
                            "GA": 0.18437476455838142,
                            "Start": 0.09331232550907986,
                            "Stub": 0.005319480261447821
                        }
                    }
                }
            },
            "800471907": {
                "articlequality": {
                    "score": {
                        "prediction": "Start",
                        "probability": {
                            "B": 0.030570319855351663,
                            "C": 0.08222898985376732,
                            "FA": 0.003910491441554669,
                            "GA": 0.010848939514677386,
                            "Start": 0.45113900388125217,
                            "Stub": 0.4213022554533967
                        }
                    }
                }
            },
            "801304355": {
                "articlequality": {
                    "score": {
                        "prediction": "Start",
                        "probability": {
                            "B": 0.06837270335849227,
                            "C": 0.4061694868257723,
                            "FA": 0.0036721100582275254,
                            "GA": 0.006669696474151564,
                            "Start": 0.5019679146777226,
                            "Stub": 0.013148088605633669
                        }
                    }
                }
            },
            "802076252": {
                "articlequality": {
                    "score": {
                        "prediction": "Start",
                        "probability": {
                            "B": 0.03530251628801977,
                            "C": 0.13940928130758615,
                            "FA": 0.006621770191372476,
                            "GA": 0.013529666366242461,
                            "Start": 0.4753718893320681,
                            "Stub": 0.32976487651471104
                        }
                    }
                }
            },
            "802855428": {
                "articlequality": {
                    "score": {
                        "prediction": "GA",
                        "probability": {
                            "B": 0.24862554340384074,
                            "C": 0.26845630598639936,
                            "FA": 0.025252061127585993,
                            "GA": 0.3761723523759918,
                            "Start": 0.07283120690469799,
                            "Stub": 0.008662530201484251
                        }
                    }
                }
            },
            "803834962": {
                "articlequality": {
                    "score": {
                        "prediction": "Start",
                        "probability": {
                            "B": 0.03650115725571478,
                            "C": 0.08636480233415172,
                            "FA": 0.004336425456662889,
                            "GA": 0.010372932140150932,
                            "Start": 0.5945172289920444,
                            "Stub": 0.26790745382127523
                        }
                    }
                }
            },
            "804579802": {
                "articlequality": {
                    "score": {
                        "prediction": "Start",
                        "probability": {
                            "B": 0.08220941621665645,
                            "C": 0.18246760182008226,
                            "FA": 0.004615246018424078,
                            "GA": 0.015509462881439935,
                            "Start": 0.6937308794719549,
                            "Stub": 0.02146739359144236
                        }
                    }
                }
            },
            "805241904": {
                "articlequality": {
                    "score": {
                        "prediction": "Start",
                        "probability": {
                            "B": 0.09529194649120816,
                            "C": 0.35586212728224725,
                            "FA": 0.005064005352925959,
                            "GA": 0.010512669685703935,
                            "Start": 0.5122316369744405,
                            "Stub": 0.021037614213474144
                        }
                    }
                }
            },
            "805875592": {
                "articlequality": {
                    "score": {
                        "prediction": "Start",
                        "probability": {
                            "B": 0.0316636303780561,
                            "C": 0.08078647008040711,
                            "FA": 0.005404569900169245,
                            "GA": 0.008386113797197703,
                            "Start": 0.6466238567313597,
                            "Stub": 0.22713535911281021
                        }
                    }
                }
            },
            "806478787": {
                "articlequality": {
                    "score": {
                        "prediction": "Stub",
                        "probability": {
                            "B": 0.007091459234524621,
                            "C": 0.009932768106635086,
                            "FA": 0.001386636540903242,
                            "GA": 0.0026201579173386474,
                            "Start": 0.030027006003879923,
                            "Stub": 0.9489419721967185
                        }
                    }
                }
            },
            "807044048": {
                "articlequality": {
                    "score": {
                        "prediction": "C",
                        "probability": {
                            "B": 0.10525394185502912,
                            "C": 0.49490815978745833,
                            "FA": 0.008212320013528812,
                            "GA": 0.06449653202690675,
                            "Start": 0.31959797221659103,
                            "Stub": 0.007531074100485776
                        }
                    }
                }
            },
            "807476738": {
                "articlequality": {
                    "score": {
                        "prediction": "C",
                        "probability": {
                            "B": 0.36990860103013795,
                            "C": 0.45909969268631146,
                            "FA": 0.018742139306555262,
                            "GA": 0.12398183396100664,
                            "Start": 0.023102293407632115,
                            "Stub": 0.005165439608356614
                        }
                    }
                }
            }
        }
    }
}