{
    "enwiki": {
        "models": {
            "articlequality": {
                "version": "0.8.2"
            }
        },
        "scores": {
            "687159391": {
                "articlequality": {
                    "score": {
                        "prediction": "Start",
                        "probability": {
                            "B": 0.035411793565166536,
                            "C": 0.07249693424355623,
                            "FA": 0.0039864588884527315,
                            "GA": 0.008792371807677637,
                            "Start": 0.5406597352095488,
                            "Stub": 0.338652706285598
                        }
                    }
                }
            },
            "707380950": {
                "articlequality": {
                    "score": {
                        "prediction": "Stub",
                        "probability": {
                            "B": 0.006395750879754352,
                            "C": 0.006893771624597458,
                            "FA": 0.0011261327005561686,
                            "GA": 0.0017865474432121316,
                            "Start": 0.015627080644569892,
                            "Stub": 0.9681707167073098
                        }
                    }
                }
            },
            "712881543": {
                "articlequality": {
                    "error": {
                        "message": "RevisionNotFound: Could not find revision ({revision}:712881543)",
                        "type": "RevisionNotFound"
                    }
                }
            },
            "716540775": {
                "articlequality": {
                    "score": {
                        "prediction": "Stub",
                        "probability": {
                            "B": 0.013095188220019252,
                            "C": 0.025660883871836643,
                            "FA": 0.00218378520877173,
                            "GA": 0.0055300509566187424,
                            "Start": 0.17871067322660716,
                            "Stub": 0.7748194185161464
                        }
                    }
                }
            },
            "719988831": {
                "articlequality": {
                    "score": {
                        "prediction": "Stub",
                        "probability": {
                            "B": 0.010330529125050497,
                            "C": 0.027025786179730008,
                            "FA": 0.001403433579619139,
                            "GA": 0.003014021816316544,
                            "Start": 0.04791749844950629,
                            "Stub": 0.9103087308497776
                        }
                    }
                }
            },
            "723322611": {
                "articlequality": {
                    "score": {
                        "prediction": "Start",
                        "probability": {
                            "B": 0.029455330126565718,
                            "C": 0.04913926347485575,
                            "FA": 0.003924962785719655,
                            "GA": 0.007398677756407238,
                            "Start": 0.5560240436688304,
                            "Stub": 0.35405772218762127
                        }
                    }
                }
            },
            "726692285": {
                "articlequality": {
                    "score": {
                        "prediction": "Start",
                        "probability": {
                            "B": 0.07649954693871736,
                            "C": 0.06656108556814369,
                            "FA": 0.003943160489390728,
                            "GA": 0.006398107484564879,
                            "Start": 0.7713458239942066,
                            "Stub": 0.07525227552497679
                        }
                    }
                }
            },
            "733935344": {
                "articlequality": {
                    "score": {
                        "prediction": "Stub",
                        "probability": {
                            "B": 0.0056092762002670285,
                            "C": 0.00617544702593283,
                            "FA": 0.0010188335747626845,
                            "GA": 0.0015887268752077606,
                            "Start": 0.010824708507581748,
                            "Stub": 0.9747830078162478
                        }
                    }
                }
            },
            "739405377": {
                "articlequality": {
                    "score": {
                        "prediction": "Stub",
                        "probability": {
                            "B": 0.007774390752677465,
                            "C": 0.009250612976668458,
                            "FA": 0.001386041212997019,
                            "GA": 0.002126700139342006,
                            "Start": 0.033548442092677426,
                            "Stub": 0.9459138128256376
                        }
                    }
                }
            },
            "745748422": {
                "articlequality": {
                    "score": {
                        "prediction": "Start",
                        "probability": {
                            "B": 0.02242271475864082,
                            "C": 0.0541084644080889,
                            "FA": 0.003693187817326465,
                            "GA": 0.006406186259158027,
                            "Start": 0.579055180968133,
                            "Stub": 0.33431426578865264
                        }
                    }
                }
            },
            "749748234": {
                "articlequality": {
                    "score": {
                        "prediction": "Start",
                        "probability": {
                            "B": 0.021721996010557274,
                            "C": 0.06480111929089345,
                            "FA": 0.0037426487740106697,
                            "GA": 0.0070141676154536784,
                            "Start": 0.5536889697341184,
                            "Stub": 0.3490310985749665
                        }
                    }
                }
            },
            "755821847": {
                "articlequality": {
                    "score": {
                        "prediction": "Stub",
                        "probability": {
                            "B": 0.019942570414648073,
                            "C": 0.03656743891603592,
                            "FA": 0.00291867188741798,
                            "GA": 0.0047865385678922175,
                            "Start": 0.35290511033835836,
                            "Stub": 0.5828796698756474
                        }
                    }
                }
            },
            "757214298": {
                "articlequality": {
                    "score": {
                        "prediction": "Stub",
                        "probability": {
                            "B": 0.008466057487968384,
                            "C": 0.012321186630711273,
                            "FA": 0.0016062684442666936,
                            "GA": 0.003274650993752188,
                            "Start": 0.05605272447758234,
                            "Stub": 0.9182791119657191
                        }
                    }
                }
            },
            "757681177": {
                "articlequality": {
                    "score": {
                        "prediction": "Start",
                        "probability": {
                            "B": 0.03369313061586228,
                            "C": 0.12164841168541231,
                            "FA": 0.0050143583090265075,
                            "GA": 0.015545465093470797,
                            "Start": 0.4332032931494717,
                            "Stub": 0.39089534114675645
                        }
                    }
                }
            },
            "762227208": {
                "articlequality": {
                    "score": {
                        "prediction": "Start",
                        "probability": {
                            "B": 0.11333239508293831,
                            "C": 0.17257411808714432,
                            "FA": 0.0036304416188412242,
                            "GA": 0.011613033816308587,
                            "Start": 0.6764642732499964,
                            "Stub": 0.022385738144771194
                        }
                    }
                }
            },
            "766481345": {
                "articlequality": {
                    "score": {
                        "prediction": "C",
                        "probability": {
                            "B": 0.16010452109928086,
                            "C": 0.5332285995638939,
                            "FA": 0.007683700463114537,
                            "GA": 0.017590756675053335,
                            "Start": 0.2719790727759968,
                            "Stub": 0.009413349422660667
                        }
                    }
                }
            },
            "770308464": {
                "articlequality": {
                    "score": {
                        "prediction": "Start",
                        "probability": {
                            "B": 0.02641399558117898,
                            "C": 0.06524766033447117,
                            "FA": 0.004056842439576352,
                            "GA": 0.008801976664394268,
                            "Start": 0.7018669875227109,
                            "Stub": 0.19361253745766832
                        }
                    }
                }
            },
            "773772420": {
                "articlequality": {
                    "score": {
                        "prediction": "Stub",
                        "probability": {
                            "B": 0.006843778596089069,
                            "C": 0.007121665877420071,
                            "FA": 0.0013192904045871748,
                            "GA": 0.001997802806512743,
                            "Start": 0.021094147281081027,
                            "Stub": 0.9616233150343101
                        }
                    }
                }
            },
            "776950217": {
                "articlequality": {
                    "score": {
                        "prediction": "Stub",
                        "probability": {
                            "B": 0.012756646903821325,
                            "C": 0.023321441214080283,
                            "FA": 0.0022702011045666777,
                            "GA": 0.004754655086412526,
                            "Start": 0.1437428579063725,
                            "Stub": 0.8131541977847465
                        }
                    }
                }
            },
            "779488031": {
                "articlequality": {
                    "score": {
                        "prediction": "Start",
                        "probability": {
                            "B": 0.05853477651503459,
                            "C": 0.12455525143232718,
                            "FA": 0.005538354610278694,
                            "GA": 0.01728687598889277,
                            "Start": 0.7126392588652065,
                            "Stub": 0.08144548258826022
                        }
                    }
                }
            },
            "782141370": {
                "articlequality": {
                    "score": {
                        "prediction": "Start",
                        "probability": {
                            "B": 0.04209657544286641,
                            "C": 0.1600020229835893,
                            "FA": 0.0037240586751712073,
                            "GA": 0.00793313288527163,
                            "Start": 0.744711384410706,
                            "Stub": 0.041532825602395504
                        }
                    }
                }
            },
            "784057010": {
                "articlequality": {
                    "score": {
                        "prediction": "Start",
                        "probability": {
                            "B": 0.035353778643977055,
                            "C": 0.09059280782307748,
                            "FA": 0.004581240466459905,
                            "GA": 0.00758880112064118,
                            "Start": 0.8100955613339453,
                            "Stub": 0.05178781061189905
                        }
                    }
                }
            },
            "786230150": {
                "articlequality": {
                    "score": {
                        "prediction": "Stub",
                        "probability": {
                            "B": 0.008282546604626448,
                            "C": 0.016742641394297885,
                            "FA": 0.0016732861108904212,
                            "GA": 0.0038892597881760977,
                            "Start": 0.052540227319047325,
                            "Stub": 0.916872038782962
                        }
                    }
                }
            },
            "787611475": {
                "articlequality": {
                    "score": {
                        "prediction": "C",
                        "probability": {
                            "B": 0.2993920896020267,
                            "C": 0.3858398017470376,
                            "FA": 0.022676163955660373,
                            "GA": 0.2335933065684369,
                            "Start": 0.049691892794334135,
                            "Stub": 0.008806745332504482
                        }
                    }
                }
            },
            "788509213": {
                "articlequality": {
                    "score": {
                        "prediction": "Stub",
                        "probability": {
                            "B": 0.014581225847663682,
                            "C": 0.027341995157041582,
                            "FA": 0.00233221181749446,
                            "GA": 0.0057779549668601216,
                            "Start": 0.2483779075680135,
                            "Stub": 0.7015887046429266
                        }
                    }
                }
            },
            "788815417": {
                "articlequality": {
                    "score": {
                        "prediction": "Stub",
                        "probability": {
                            "B": 0.009652954011451434,
                            "C": 0.01286795028764751,
                            "FA": 0.0018762579796138084,
                            "GA": 0.003832366026464712,
                            "Start": 0.05424364515430182,
                            "Stub": 0.9175268265405206
                        }
                    }
                }
            },
            "788946973": {
                "articlequality": {
                    "score": {
                        "prediction": "Stub",
                        "probability": {
                            "B": 0.009579693674245535,
                            "C": 0.01643707485316985,
                            "FA": 0.0016047565462541068,
                            "GA": 0.003089355325783903,
                            "Start": 0.1093464853448045,
                            "Stub": 0.859942634255742
                        }
                    }
                }
            },
            "789275446": {
                "articlequality": {
                    "score": {
                        "prediction": "Stub",
                        "probability": {
                            "B": 0.008676083259529696,
                            "C": 0.010162391808056193,
                            "FA": 0.0013338204737447902,
                            "GA": 0.0022288622620738187,
                            "Start": 0.031127343854316515,
                            "Stub": 0.9464714983422791
                        }
                    }
                }
            },
            "789334867": {
                "articlequality": {
                    "score": {
                        "prediction": "Stub",
                        "probability": {
                            "B": 0.028998160992323795,
                            "C": 0.07232007557085053,
                            "FA": 0.003585130220671739,
                            "GA": 0.009845285789865158,
                            "Start": 0.34402230343667595,
                            "Stub": 0.5412290439896128
                        }
                    }
                }
            },
            "790006261": {
                "articlequality": {
                    "score": {
                        "prediction": "Stub",
                        "probability": {
                            "B": 0.0076119630597871295,
                            "C": 0.008383927222795691,
                            "FA": 0.0015171728229627084,
                            "GA": 0.002134714915065607,
                            "Start": 0.043162361474638526,
                            "Stub": 0.9371898605047504
                        }
                    }
                }
            },
            "790924186": {
                "articlequality": {
                    "score": {
                        "prediction": "Start",
                        "probability": {
                            "B": 0.023512593978128476,
                            "C": 0.060565020963817384,
                            "FA": 0.004099371165261182,
                            "GA": 0.008685820615320554,
                            "Start": 0.5259494611754292,
                            "Stub": 0.3771877321020433
                        }
                    }
                }
            },
            "792296715": {
                "articlequality": {
                    "score": {
                        "prediction": "Start",
                        "probability": {
                            "B": 0.030089603878564578,
                            "C": 0.03406399017229198,
                            "FA": 0.004755069334173189,
                            "GA": 0.007007206722236089,
                            "Start": 0.5071128429286533,
                            "Stub": 0.41697128696408087
                        }
                    }
                }
            },
            "793748545": {
                "articlequality": {
                    "score": {
                        "prediction": "Stub",
                        "probability": {
                            "B": 0.009376797233159345,
                            "C": 0.013315103333573637,
                            "FA": 0.00181847684659439,
                            "GA": 0.003766351525135526,
                            "Start": 0.08846918899218441,
                            "Stub": 0.8832540820693526
                        }
                    }
                }
            },
            "795054169": {
                "articlequality": {
                    "score": {
                        "prediction": "Stub",
                        "probability": {
                            "B": 0.01039005260649425,
                            "C": 0.01785351266890809,
                            "FA": 0.0014491623930018675,
                            "GA": 0.003655219360784184,
                            "Start": 0.09484738014635263,
                            "Stub": 0.871804672824459
                        }
                    }
                }
            },
            "796304094": {
                "articlequality": {
                    "score": {
                        "prediction": "Start",
                        "probability": {
                            "B": 0.03808395039085012,
                            "C": 0.1613695181351881,
                            "FA": 0.00450663801236201,
                            "GA": 0.010424223042482588,
                            "Start": 0.6979385015058044,
                            "Stub": 0.08767716891331291
                        }
                    }
                }
            },
            "797346875": {
                "articlequality": {
                    "score": {
                        "prediction": "Stub",
                        "probability": {
                            "B": 0.006079223563489196,
                            "C": 0.008371036818928484,
                            "FA": 0.0011272201701222682,
                            "GA": 0.002400227043993164,
                            "Start": 0.014795135615663141,
                            "Stub": 0.9672271567878038
                        }
                    }
                }
            },
            "798391286": {
                "articlequality": {
                    "score": {
                        "prediction": "Stub",
                        "probability": {
                            "B": 0.011840752961965807,
                            "C": 0.01823969151466728,
                            "FA": 0.002166133062347074,
                            "GA": 0.004540776195288252,
                            "Start": 0.17227762213257106,
                            "Stub": 0.7909350241331605
                        }
                    }
                }
            },
            "799237748": {
                "articlequality": {
                    "score": {
                        "prediction": "C",
                        "probability": {
                            "B": 0.11505223683015774,
                            "C": 0.5991551302779999,
                            "FA": 0.006374202429971539,
                            "GA": 0.011660166475802272,
                            "Start": 0.2569319580984751,
                            "Stub": 0.010826305887593137
                        }
                    }
                }
            },
            "800116899": {
                "articlequality": {
                    "score": {
                        "prediction": "Start",
                        "probability": {
                            "B": 0.04998601504399388,
                            "C": 0.04010049077680989,
                            "FA": 0.0035937648839688163,
                            "GA": 0.005612308449476076,
                            "Start": 0.869308578828336,
                            "Stub": 0.03139884201741546
                        }
                    }
                }
            },
            "800884377": {
                "articlequality": {
                    "score": {
                        "prediction": "Stub",
                        "probability": {
                            "B": 0.005807866909627409,
                            "C": 0.007492919307594178,
                            "FA": 0.001060306876792131,
                            "GA": 0.0020462581947170433,
                            "Start": 0.01416825221436616,
                            "Stub": 0.9694243964969029
                        }
                    }
                }
            },
            "801554031": {
                "articlequality": {
                    "score": {
                        "prediction": "Stub",
                        "probability": {
                            "B": 0.015331753639959379,
                            "C": 0.024955059004994635,
                            "FA": 0.002957591086292257,
                            "GA": 0.0054460179650896836,
                            "Start": 0.33393448626531963,
                            "Stub": 0.6173750920383444
                        }
                    }
                }
            },
            "802440511": {
                "articlequality": {
                    "score": {
                        "prediction": "C",
                        "probability": {
                            "B": 0.4324275976613075,
                            "C": 0.4336032461526829,
                            "FA": 0.007642454900114621,
                            "GA": 0.015910782402940648,
                            "Start": 0.10411263799550147,
                            "Stub": 0.006303280887452604
                        }
                    }
                }
            },
            "803291629": {
                "articlequality": {
                    "score": {
                        "prediction": "Start",
                        "probability": {
                            "B": 0.1961586251206952,
                            "C": 0.3052956689041403,
                            "FA": 0.00660753216005096,
                            "GA": 0.01296199040923912,
                            "Start": 0.45555264658471467,
                            "Stub": 0.023423536821159885
                        }
                    }
                }
            },
            "804133555": {
                "articlequality": {
                    "score": {
                        "prediction": "Start",
                        "probability": {
                            "B": 0.02834310417071875,
                            "C": 0.053993190172710946,
                            "FA": 0.005874776083955776,
                            "GA": 0.006868951941517645,
                            "Start": 0.8050848495321279,
                            "Stub": 0.09983512809896888
                        }
                    }
                }
            },
            "804931752": {
                "articlequality": {
                    "score": {
                        "prediction": "Start",
                        "probability": {
                            "B": 0.04125528190982382,
                            "C": 0.06463032220189385,
                            "FA": 0.004747501088774338,
                            "GA": 0.012470766944090892,
                            "Start": 0.4709767047360526,
                            "Stub": 0.40591942311936463
                        }
                    }
                }
            },
            "805511480": {
                "articlequality": {
                    "score": {
                        "prediction": "C",
                        "probability": {
                            "B": 0.14168905264965526,
                            "C": 0.4078185264643805,
                            "FA": 0.007207815013844,
                            "GA": 0.21527800128112537,
                            "Start": 0.2140569936599141,
                            "Stub": 0.013949610931080807
                        }
                    }
                }
            },
            "806165389": {
                "articlequality": {
                    "score": {
                        "prediction": "GA",
                        "probability": {
                            "B": 0.08244783618510008,
                            "C": 0.0364753280766116,
                            "FA": 0.28072652165462336,
                            "GA": 0.5850409321868737,
                            "Start": 0.010834287806511366,
                            "Stub": 0.004475094090279933
                        }
                    }
                }
            },
            "806714631": {
                "articlequality": {
                    "score": {
                        "prediction": "Start",
                        "probability": {
                            "B": 0.030722585745798687,
                            "C": 0.06525806643756055,
                            "FA": 0.003322098305443511,
                            "GA": 0.0055392598109511694,
                            "Start": 0.8140806655582498,
                            "Stub": 0.08107732414199642
                        }
                    }
                }
            },
            "807253396": {
                "articlequality": {
                    "score": {
                        "prediction": "Start",
                        "probability": {
                            "B": 0.2273184935370082,
                            "C": 0.18033837740052466,
                            "FA": 0.009116058954333858,
                            "GA": 0.010653707846354686,
                            "Start": 0.56031979912063,
                            "Stub": 0.012253563141148484
                        }
                    }
                }
            }
        }
    }
}