{
    "enwiki": {
        "models": {
            "articlequality": {
                "version": "0.8.2"
            }
        },
        "scores": {
            "647367482": {
                "articlequality": {
                    "score": {
                        "prediction": "Start",
                        "probability": {
                            "B": 0.09677032449312493,
                            "C": 0.31288778881518875,
                            "FA": 0.005923059640388157,
                            "GA": 0.008264655953089462,
                            "Start": 0.5383577818599297,
                            "Stub": 0.03779638923827897
                        }
                    }
                }
            },
            "706211513": {
                "articlequality": {
                    "score": {
                        "prediction": "Start",
                        "probability": {
                            "B": 0.0613972307163985,
                            "C": 0.10073770418569908,
                            "FA": 0.005905213209784524,
                            "GA": 0.010783101782855185,
                            "Start": 0.7773432489586871,
                            "Stub": 0.04383350114657563
                        }
                    }
                }
            },
            "711603471": {
                "articlequality": {
                    "score": {
                        "prediction": "Start",
                        "probability": {
                            "B": 0.19551529088268182,
                            "C": 0.06027500306591438,
                            "FA": 0.0034712745107851575,
                            "GA": 0.005165330117381754,
                            "Start": 0.6018204964066838,
                            "Stub": 0.13375260501655314
                        }
                    }
                }
            },
            "715533871": {
                "articlequality": {
                    "score": {
                        "prediction": "Stub",
                        "probability": {
                            "B": 0.007731154638007143,
                            "C": 0.0075699083045067395,
                            "FA": 0.0014381826832713378,
                            "GA": 0.002146166209539205,
                            "Start": 0.02934396607857271,
                            "Stub": 0.9517706220861029
                        }
                    }
                }
            },
            "719010117": {
                "articlequality": {
                    "score": {
                        "prediction": "Stub",
                        "probability": {
                            "B": 0.006316450120001484,
                            "C": 0.008535539415092688,
                            "FA": 0.001170907958201861,
                            "GA": 0.0021900392648519385,
                            "Start": 0.02093179690270114,
                            "Stub": 0.9608552663391507
                        }
                    }
                }
            },
            "722394284": {
                "articlequality": {
                    "score": {
                        "prediction": "Stub",
                        "probability": {
                            "B": 0.006298285655606371,
                            "C": 0.007109850289379559,
                            "FA": 0.0010915217231553746,
                            "GA": 0.0017575872373522656,
                            "Start": 0.013652046950764938,
                            "Stub": 0.9700907081437413
                        }
                    }
                }
            },
            "725657037": {
                "articlequality": {
                    "score": {
                        "prediction": "Stub",
                        "probability": {
                            "B": 0.00543151074373115,
                            "C": 0.007443228415210642,
                            "FA": 0.0010925712873590748,
                            "GA": 0.0022163542167063636,
                            "Start": 0.017746447452212138,
                            "Stub": 0.9660698878847807
                        }
                    }
                }
            },
            "732422122": {
                "articlequality": {
                    "score": {
                        "prediction": "Stub",
                        "probability": {
                            "B": 0.0074068965850403725,
                            "C": 0.008193365802845402,
                            "FA": 0.0013056457559701114,
                            "GA": 0.0020086706547966216,
                            "Start": 0.027476820942063274,
                            "Stub": 0.9536086002592842
                        }
                    }
                }
            },
            "738199614": {
                "articlequality": {
                    "score": {
                        "prediction": "C",
                        "probability": {
                            "B": 0.20784431073217663,
                            "C": 0.4291882488452122,
                            "FA": 0.007378901443057697,
                            "GA": 0.017727987235364246,
                            "Start": 0.3085132038967666,
                            "Stub": 0.02934734784742247
                        }
                    }
                }
            },
            "744454070": {
                "articlequality": {
                    "score": {
                        "prediction": "Start",
                        "probability": {
                            "B": 0.08238884464097121,
                            "C": 0.10998338011616851,
                            "FA": 0.004381480877731378,
                            "GA": 0.024620032120406674,
                            "Start": 0.42389873609341366,
                            "Stub": 0.35472752615130854
                        }
                    }
                }
            },
            "749318494": {
                "articlequality": {
                    "score": {
                        "prediction": "Start",
                        "probability": {
                            "B": 0.03466640175784727,
                            "C": 0.11532710067312128,
                            "FA": 0.005413347180995219,
                            "GA": 0.016912908021847715,
                            "Start": 0.4301711259696984,
                            "Stub": 0.39750911639648995
                        }
                    }
                }
            },
            "754400016": {
                "articlequality": {
                    "score": {
                        "prediction": "Start",
                        "probability": {
                            "B": 0.0302438144264383,
                            "C": 0.09770059976637481,
                            "FA": 0.004370967260496532,
                            "GA": 0.008095391972443884,
                            "Start": 0.5157323257721631,
                            "Stub": 0.3438569008020833
                        }
                    }
                }
            },
            "757153690": {
                "articlequality": {
                    "score": {
                        "prediction": "Stub",
                        "probability": {
                            "B": 0.00764800962702511,
                            "C": 0.010391803046370723,
                            "FA": 0.00150924426944717,
                            "GA": 0.0028541149819133376,
                            "Start": 0.03002136534861207,
                            "Stub": 0.9475754627266315
                        }
                    }
                }
            },
            "757561950": {
                "articlequality": {
                    "score": {
                        "prediction": "Start",
                        "probability": {
                            "B": 0.021800333230892966,
                            "C": 0.02353948778499509,
                            "FA": 0.0034374950398757638,
                            "GA": 0.005742684175394591,
                            "Start": 0.6698016244427171,
                            "Stub": 0.27567837532612455
                        }
                    }
                }
            },
            "760751159": {
                "articlequality": {
                    "score": {
                        "prediction": "C",
                        "probability": {
                            "B": 0.2110215165286837,
                            "C": 0.5812966537521548,
                            "FA": 0.006532731246158838,
                            "GA": 0.03604700456313757,
                            "Start": 0.15694078354255084,
                            "Stub": 0.00816131036731419
                        }
                    }
                }
            },
            "765515183": {
                "articlequality": {
                    "score": {
                        "prediction": "Start",
                        "probability": {
                            "B": 0.05953952312857539,
                            "C": 0.06165564542597492,
                            "FA": 0.0049054402142306944,
                            "GA": 0.007859264282635692,
                            "Start": 0.7363406496283391,
                            "Stub": 0.1296994773202442
                        }
                    }
                }
            },
            "769257953": {
                "articlequality": {
                    "score": {
                        "prediction": "Stub",
                        "probability": {
                            "B": 0.025650081302058175,
                            "C": 0.04537987072337322,
                            "FA": 0.0031985268984264475,
                            "GA": 0.006177827333005516,
                            "Start": 0.4375478548160024,
                            "Stub": 0.4820458389271343
                        }
                    }
                }
            },
            "772923354": {
                "articlequality": {
                    "score": {
                        "prediction": "Stub",
                        "probability": {
                            "B": 0.008892987930244328,
                            "C": 0.011715235001252074,
                            "FA": 0.0015213185509832105,
                            "GA": 0.0023742228247847414,
                            "Start": 0.05953269465424148,
                            "Stub": 0.9159635410384941
                        }
                    }
                }
            },
            "776286813": {
                "articlequality": {
                    "score": {
                        "prediction": "Start",
                        "probability": {
                            "B": 0.04077752799734264,
                            "C": 0.13512264772202023,
                            "FA": 0.0053548230411538675,
                            "GA": 0.013591970956706518,
                            "Start": 0.507746069096366,
                            "Stub": 0.2974069611864107
                        }
                    }
                }
            },
            "779069904": {
                "articlequality": {
                    "score": {
                        "prediction": "Start",
                        "probability": {
                            "B": 0.11390032000742448,
                            "C": 0.227033092823884,
                            "FA": 0.004681137487703887,
                            "GA": 0.008995089398199173,
                            "Start": 0.6238699712360144,
                            "Stub": 0.021520389046774186
                        }
                    }
                }
            },
            "781324428": {
                "articlequality": {
                    "score": {
                        "prediction": "Start",
                        "probability": {
                            "B": 0.025642718336203244,
                            "C": 0.06339794444101747,
                            "FA": 0.004439281273642006,
                            "GA": 0.00856342368844881,
                            "Start": 0.45172658658700887,
                            "Stub": 0.44623004567367947
                        }
                    }
                }
            },
            "783606376": {
                "articlequality": {
                    "score": {
                        "prediction": "Stub",
                        "probability": {
                            "B": 0.010434067814404492,
                            "C": 0.020599266335096032,
                            "FA": 0.0017487314438613365,
                            "GA": 0.004195377867895304,
                            "Start": 0.06274723775535086,
                            "Stub": 0.900275318783392
                        }
                    }
                }
            },
            "785759881": {
                "articlequality": {
                    "score": {
                        "prediction": "C",
                        "probability": {
                            "B": 0.17221168391239355,
                            "C": 0.41639224917552625,
                            "FA": 0.005277537824919542,
                            "GA": 0.35778885711573405,
                            "Start": 0.04432930028442416,
                            "Stub": 0.004000371687002359
                        }
                    }
                }
            },
            "787378028": {
                "articlequality": {
                    "score": {
                        "prediction": "Start",
                        "probability": {
                            "B": 0.02309044504979823,
                            "C": 0.027001591960071538,
                            "FA": 0.0030997204179882758,
                            "GA": 0.005218988293834047,
                            "Start": 0.8004362371774952,
                            "Stub": 0.1411530171008127
                        }
                    }
                }
            },
            "788310015": {
                "articlequality": {
                    "score": {
                        "prediction": "Stub",
                        "probability": {
                            "B": 0.006840158857504381,
                            "C": 0.009334072483924054,
                            "FA": 0.0013615152010672028,
                            "GA": 0.0028532924504845792,
                            "Start": 0.024323215381646595,
                            "Stub": 0.9552877456253733
                        }
                    }
                }
            },
            "788799366": {
                "articlequality": {
                    "score": {
                        "prediction": "Stub",
                        "probability": {
                            "B": 0.007183606089795442,
                            "C": 0.01200878806029701,
                            "FA": 0.001406043755781882,
                            "GA": 0.003139877600296183,
                            "Start": 0.02527184626582154,
                            "Stub": 0.9509898382280079
                        }
                    }
                }
            },
            "788884549": {
                "articlequality": {
                    "score": {
                        "prediction": "Stub",
                        "probability": {
                            "B": 0.007601529411164242,
                            "C": 0.00889403686424209,
                            "FA": 0.0014222635267618449,
                            "GA": 0.002209768365045132,
                            "Start": 0.02277700708923436,
                            "Stub": 0.9570953947435523
                        }
                    }
                }
            },
            "789268549": {
                "articlequality": {
                    "score": {
                        "prediction": "Start",
                        "probability": {
                            "B": 0.026319324694235712,
                            "C": 0.05349840982736896,
                            "FA": 0.004150587430533793,
                            "GA": 0.00687806135486524,
                            "Start": 0.5797264718615682,
                            "Stub": 0.3294271448314281
                        }
                    }
                }
            },
            "789309956": {
                "articlequality": {
                    "score": {
                        "prediction": "Stub",
                        "probability": {
                            "B": 0.010800390732292919,
                            "C": 0.013099754572767547,
                            "FA": 0.001995455924633294,
                            "GA": 0.0030337953005933342,
                            "Start": 0.11747067479951395,
                            "Stub": 0.8535999286701988
                        }
                    }
                }
            },
            "789814956": {
                "articlequality": {
                    "score": {
                        "prediction": "Stub",
                        "probability": {
                            "B": 0.005200516579883481,
                            "C": 0.0059811422485909465,
                            "FA": 0.0009546277306321967,
                            "GA": 0.0015019949676301266,
                            "Start": 0.010907283830094615,
                            "Stub": 0.9754544346431686
                        }
                    }
                }
            },
            "790608224": {
                "articlequality": {
                    "score": {
                        "prediction": "Start",
                        "probability": {
                            "B": 0.020925670528690883,
                            "C": 0.06199332419616897,
                            "FA": 0.0036809106776213786,
                            "GA": 0.006927519247056856,
                            "Start": 0.6011206773388877,
                            "Stub": 0.3053518980115741
                        }
                    }
                }
            },
            "791906045": {
                "articlequality": {
                    "score": {
                        "prediction": "C",
                        "probability": {
                            "B": 0.19875280511801854,
                            "C": 0.672117405408077,
                            "FA": 0.006808875541623983,
                            "GA": 0.008132678303547428,
                            "Start": 0.11046203101688272,
                            "Stub": 0.0037262046118504573
                        }
                    }
                }
            },
            "793409462": {
                "articlequality": {
                    "score": {
                        "prediction": "Stub",
                        "probability": {
                            "B": 0.005665262445635333,
                            "C": 0.007424479819934452,
                            "FA": 0.0010970376873110444,
                            "GA": 0.0021794330870151513,
                            "Start": 0.013064007100877418,
                            "Stub": 0.9705697798592267
                        }
                    }
                }
            },
            "794796636": {
                "articlequality": {
                    "score": {
                        "prediction": "Start",
                        "probability": {
                            "B": 0.1891781676242471,
                            "C": 0.2544813115215805,
                            "FA": 0.006471646581035364,
                            "GA": 0.010414765038689553,
                            "Start": 0.5239553067052791,
                            "Stub": 0.015498802529168356
                        }
                    }
                }
            },
            "796006443": {
                "articlequality": {
                    "score": {
                        "prediction": "C",
                        "probability": {
                            "B": 0.11841558956982728,
                            "C": 0.561549015077152,
                            "FA": 0.005244867730796557,
                            "GA": 0.01012906911932437,
                            "Start": 0.2976527554629965,
                            "Stub": 0.007008703039903122
                        }
                    }
                }
            },
            "797086564": {
                "articlequality": {
                    "score": {
                        "prediction": "C",
                        "probability": {
                            "B": 0.15843882382943186,
                            "C": 0.4430938270193694,
                            "FA": 0.005591414057180189,
                            "GA": 0.06616681951748647,
                            "Start": 0.3208275928698178,
                            "Stub": 0.005881522706714271
                        }
                    }
                }
            },
            "798143123": {
                "articlequality": {
                    "score": {
                        "prediction": "Stub",
                        "probability": {
                            "B": 0.006599771038452909,
                            "C": 0.00966022554606482,
                            "FA": 0.001343372684021867,
                            "GA": 0.002918584326298915,
                            "Start": 0.0389487117370634,
                            "Stub": 0.9405293346680981
                        }
                    }
                }
            },
            "799021548": {
                "articlequality": {
                    "score": {
                        "prediction": "Stub",
                        "probability": {
                            "B": 0.008501191204329793,
                            "C": 0.011614021917575625,
                            "FA": 0.0014583405998889753,
                            "GA": 0.0028309334609243723,
                            "Start": 0.0682623176789858,
                            "Stub": 0.9073331951382955
                        }
                    }
                }
            },
            "799888924": {
                "articlequality": {
                    "score": {
                        "prediction": "Stub",
                        "probability": {
                            "B": 0.006278500170856481,
                            "C": 0.009702460304146768,
                            "FA": 0.0012468824017881233,
                            "GA": 0.0029479910766518724,
                            "Start": 0.019870580059838525,
                            "Stub": 0.9599535859867182
                        }
                    }
                }
            },
            "800666029": {
                "articlequality": {
                    "score": {
                        "prediction": "Start",
                        "probability": {
                            "B": 0.021462783367801386,
                            "C": 0.03222166144436001,
                            "FA": 0.0035625242556087374,
                            "GA": 0.006230193509858694,
                            "Start": 0.5211203528300927,
                            "Stub": 0.41540248459227846
                        }
                    }
                }
            },
            "801399254": {
                "articlequality": {
                    "score": {
                        "prediction": "C",
                        "probability": {
                            "B": 0.2669431447877507,
                            "C": 0.3655229398464765,
                            "FA": 0.0054943974838754005,
                            "GA": 0.014432606223928095,
                            "Start": 0.3379233211504738,
                            "Stub": 0.009683590507495416
                        }
                    }
                }
            },
            "802286203": {
                "articlequality": {
                    "score": {
                        "prediction": "Stub",
                        "probability": {
                            "B": 0.012575330758684554,
                            "C": 0.024929537629112184,
                            "FA": 0.002379420387777317,
                            "GA": 0.004925802941121788,
                            "Start": 0.2026051999472823,
                            "Stub": 0.752584708336022
                        }
                    }
                }
            },
            "803035632": {
                "articlequality": {
                    "score": {
                        "prediction": "Start",
                        "probability": {
                            "B": 0.04723069489237623,
                            "C": 0.14765805516854041,
                            "FA": 0.004723027003947121,
                            "GA": 0.009301447747144889,
                            "Start": 0.5049905939099573,
                            "Stub": 0.28609618127803416
                        }
                    }
                }
            },
            "803960537": {
                "articlequality": {
                    "score": {
                        "prediction": "Stub",
                        "probability": {
                            "B": 0.00758382824006935,
                            "C": 0.010446104511637412,
                            "FA": 0.0015173937634042308,
                            "GA": 0.003338467129869035,
                            "Start": 0.023863785659215552,
                            "Stub": 0.9532504206958043
                        }
                    }
                }
            },
            "804742168": {
                "articlequality": {
                    "score": {
                        "prediction": "Start",
                        "probability": {
                            "B": 0.05103729699690874,
                            "C": 0.03923489004067235,
                            "FA": 0.0037844889835343416,
                            "GA": 0.005849471483768919,
                            "Start": 0.8337830812771452,
                            "Stub": 0.06631077121797056
                        }
                    }
                }
            },
            "805365142": {
                "articlequality": {
                    "score": {
                        "prediction": "Stub",
                        "probability": {
                            "B": 0.015927425747657608,
                            "C": 0.01838471959812326,
                            "FA": 0.0016863937336509531,
                            "GA": 0.003332314338980134,
                            "Start": 0.06820312767409004,
                            "Stub": 0.8924660189074979
                        }
                    }
                }
            },
            "805994428": {
                "articlequality": {
                    "score": {
                        "prediction": "Stub",
                        "probability": {
                            "B": 0.013519599540124362,
                            "C": 0.013180285244684151,
                            "FA": 0.0020613790534194606,
                            "GA": 0.0033012536832696168,
                            "Start": 0.08882893433775797,
                            "Stub": 0.8791085481407445
                        }
                    }
                }
            },
            "806578497": {
                "articlequality": {
                    "score": {
                        "prediction": "Stub",
                        "probability": {
                            "B": 0.0100023293774905,
                            "C": 0.01442596468157268,
                            "FA": 0.0018419785701913305,
                            "GA": 0.0036576747081093976,
                            "Start": 0.034210042129840794,
                            "Stub": 0.9358620105327953
                        }
                    }
                }
            },
            "807150766": {
                "articlequality": {
                    "score": {
                        "prediction": "C",
                        "probability": {
                            "B": 0.11656662056261534,
                            "C": 0.5401010611228448,
                            "FA": 0.01571691123515106,
                            "GA": 0.2357269810023765,
                            "Start": 0.08545988036169799,
                            "Stub": 0.00642854571531429
                        }
                    }
                }
            }
        }
    }
}